eyja_users/__init__.py
eyja_users/api/__init__.py
eyja_users/api/dynamic_api/__init__.py
eyja_users/api/dynamic_api/model_api.py
eyja_users/api/routes/__init__.py
eyja_users/api/routes/confirm.py
eyja_users/api/routes/current.py
eyja_users/api/routes/login.py
eyja_users/api/routes/logout.py
eyja_users/api/routes/registration.py
eyja_users/api/routes/router.py
eyja_users/decorators/__init__.py
eyja_users/decorators/auth.py
eyja_users/errors/__init__.py
eyja_users/errors/misc_errors.py
eyja_users/errors/user_errors.py
eyja_users/helpers/__init__.py
eyja_users/helpers/models.py
eyja_users/interfaces/__init__.py
eyja_users/interfaces/operators/__init__.py
eyja_users/interfaces/operators/authorized_model_operator.py
eyja_users/middleware/__init__.py
eyja_users/middleware/auth.py
eyja_users/models/__init__.py
eyja_users/models/access_token.py
eyja_users/models/confirm_token.py
eyja_users/models/refresh_token.py
eyja_users/models/user.py
eyja_users/models/user_mixin.py
eyja_users/operators/__init__.py
eyja_users/operators/access_token/__init__.py
eyja_users/operators/access_token/constants.py
eyja_users/operators/access_token/operator.py
eyja_users/operators/confirm_token/__init__.py
eyja_users/operators/confirm_token/constants.py
eyja_users/operators/confirm_token/operator.py
eyja_users/operators/confirm_token/types.py
eyja_users/operators/refresh_token/__init__.py
eyja_users/operators/refresh_token/constants.py
eyja_users/operators/refresh_token/operator.py
eyja_users/operators/refresh_token/statuses.py
eyja_users/operators/user/__init__.py
eyja_users/operators/user/operator.py
eyja_users/processes/__init__.py
eyja_users/processes/user_process.py
eyja_users/processes/auth/__init__.py
eyja_users/processes/auth/authorization.py
eyja_users/processes/auth/confirm.py
eyja_users/processes/auth/refresh.py
eyja_users/processes/auth/registration.py
eyja_users/processes/auth/unauthorization.py
tests/__init__.py
tests/test_processes/__init__.py
eyja_fastapi_users-0.1.4.dist-info/METADATA
eyja_fastapi_users-0.1.4.dist-info/WHEEL
eyja_fastapi_users-0.1.4.dist-info/top_level.txt
eyja_fastapi_users-0.1.4.dist-info/zip-safe
eyja_fastapi_users-0.1.4.dist-info/RECORD
