Metadata-Version: 2.1
Name: eyja-fastapi-users
Version: 0.1.4
Summary: Eyja authentication library for FastAPI
Home-page: https://gitlab.com/public.eyja.dev/eyja-fastapi-users
Maintainer: Anton Berdnikov
Maintainer-email: agratoth@yandex.ru
License: UNKNOWN
Platform: UNKNOWN
Classifier: License :: OSI Approved :: MIT License
Classifier: Operating System :: OS Independent
Classifier: Programming Language :: Python
Classifier: Programming Language :: Python :: 3.8
Classifier: Programming Language :: Python :: 3.9
Requires-Python: >=3.8
Requires-Dist: eyja-internal (>=0.3.24)
Requires-Dist: eyja-email (>=0.1.0)
Requires-Dist: fastapi (>=0.70.1)
Requires-Dist: passlib (>=1.7.4)
